gddoc2yml/__init__.py
gddoc2yml/gdxml2xrefmap.py
gddoc2yml/gdxml2yml.py
gddoc2yml/gdxml_helpers.py
gddoc2yml/make_rst.py
gddoc2yml/version.py
gddoc2yml-1.0.0.dist-info/licenses/LICENSE
gddoc2yml-1.0.0.dist-info/METADATA
gddoc2yml-1.0.0.dist-info/WHEEL
gddoc2yml-1.0.0.dist-info/entry_points.txt
gddoc2yml-1.0.0.dist-info/top_level.txt
gddoc2yml-1.0.0.dist-info/RECORD
