Metadata-Version: 2.4
Name: gddoc2yml
Version: 1.0.0
Summary: Convert godot xml docs to docfx yml
Author-email: Nick Maltbie <nick.dmalt@gmail.com>
Project-URL: Homepage, https://github.com/nicholas-maltbie/gddoc2yml
Project-URL: Issues, https://github.com/nicholas-maltbie/gddoc2yml/issues
Project-URL: GitHub, https://github.com/nicholas-maltbie/gddoc2yml
Project-URL: Changelog, https://github.com/nicholas-maltbie/gddoc2yml/blob/main/CHANGELOG.md
Keywords: godot,docfx,yml,xml,documentation
Classifier: Development Status :: 3 - Alpha
Classifier: License :: OSI Approved :: MIT License
Classifier: Intended Audience :: Developers
Classifier: Topic :: Software Development :: Documentation
Classifier: Operating System :: OS Independent
Classifier: Programming Language :: Python :: 3
Classifier: Programming Language :: Python :: 3.9
Classifier: Programming Language :: Python :: 3.10
Classifier: Programming Language :: Python :: 3.11
Classifier: Programming Language :: Python :: 3.12
Requires-Python: >=3.9
License-File: LICENSE
Requires-Dist: pathvalidate
Requires-Dist: PyYAML
Dynamic: license-file
